pyzeal/py.typed
pyzeal/algorithms/__init__.py
pyzeal/algorithms/constants.py
pyzeal/algorithms/finder_algorithm.py
pyzeal/algorithms/newton_grid.py
pyzeal/algorithms/polynomial_holo.py
pyzeal/algorithms/simple_holo.py
pyzeal/algorithms/simple_holo_newton.py
pyzeal/algorithms/estimators/__init__.py
pyzeal/algorithms/estimators/argument_estimator.py
pyzeal/algorithms/estimators/constants.py
pyzeal/algorithms/estimators/estimator_cache.py
pyzeal/algorithms/estimators/quad_estimator.py
pyzeal/algorithms/estimators/sum_estimator.py
pyzeal/algorithms/wrappers/__init__.py
pyzeal/algorithms/wrappers/classical_polynomial.py
pyzeal/algorithms/wrappers/polynomial_wrapper.py
pyzeal/cli/__init__.py
pyzeal/cli/__main__.py
pyzeal/cli/cli_controller.py
pyzeal/cli/cli_parser.py
pyzeal/cli/controller_facade.py
pyzeal/cli/parse_results.py
pyzeal/cli/parser_facade.py
pyzeal/plugins/__init__.py
pyzeal/plugins/installation_helper.py
pyzeal/plugins/plugin_loader.py
pyzeal/plugins/pyzeal_plugin.py
pyzeal/plugins/custom_plugins/__init__.py
pyzeal/pyzeal_logging/__init__.py
pyzeal/pyzeal_logging/log_levels.py
pyzeal/pyzeal_logging/log_manager.py
pyzeal/pyzeal_logging/loggable.py
pyzeal/pyzeal_logging/logger_facade.py
pyzeal/pyzeal_types/__init__.py
pyzeal/pyzeal_types/algorithm_types.py
pyzeal/pyzeal_types/container_types.py
pyzeal/pyzeal_types/estimator_types.py
pyzeal/pyzeal_types/filter_types.py
pyzeal/pyzeal_types/init_modes.py
pyzeal/pyzeal_types/parallel_types.py
pyzeal/pyzeal_types/root_types.py
pyzeal/pyzeal_types/settings_types.py
pyzeal/rootfinders/__init__.py
pyzeal/rootfinders/finder_interface.py
pyzeal/rootfinders/parallel_finder.py
pyzeal/rootfinders/rootfinder.py
pyzeal/settings/__init__.py
pyzeal/settings/core_settings_service.py
pyzeal/settings/default_settings.json
pyzeal/settings/invalid_setting_exception.py
pyzeal/settings/json_core_settings.py
pyzeal/settings/json_helper.py
pyzeal/settings/json_settings_service.py
pyzeal/settings/ram_settings_service.py
PyZEAL-1.0.0.dist-info/LICENSE
PyZEAL-1.0.0.dist-info/METADATA
PyZEAL-1.0.0.dist-info/WHEEL
PyZEAL-1.0.0.dist-info/entry_points.txt
PyZEAL-1.0.0.dist-info/top_level.txt
PyZEAL-1.0.0.dist-info/RECORD
